tabdanc/__init__.py
tabdanc/base.py
tabdanc/command.py
tabdanc/config.py
tabdanc/run.py
tabdanc/tabdanc.default.cfg
tabdanc/update.py
tabdanc/sql/compare_tds_version.sql
tabdanc/sql/create_table.sql
tabdanc/sql/drop_table.sql
tabdanc/sql/insert_tds_version.sql
tabdanc/sql/select_table.sql
tabdanc/sql/update_tds_version.sql
tabdanc/sql/base/init_schema.sql
tabdanc/sql/base/init_table.sql
tabdanc/sql/td/copy_csv_to_table.sql
tabdanc/sql/td/insert_target_from_temp.sql
tabdanc/updownload/__init__.py
tabdanc/updownload/base.py
tabdanc/updownload/download.py
tabdanc/updownload/ssh.py
tabdanc/updownload/upload.py
tabdanc-0.0.3.dist-info/LICENSE
tabdanc-0.0.3.dist-info/METADATA
tabdanc-0.0.3.dist-info/WHEEL
tabdanc-0.0.3.dist-info/entry_points.txt
tabdanc-0.0.3.dist-info/top_level.txt
tabdanc-0.0.3.dist-info/RECORD
